AUTHORS
LICENSE
MANIFEST.in
README.rst
setup.py
src/restible_swagger/__init__.py
src/restible_swagger/decorators.py
src/restible_swagger/endpoint.py
src/restible_swagger/logic.py
src/restible_swagger/route.py
src/restible_swagger/util.py
src/restible_swagger.egg-info/PKG-INFO
src/restible_swagger.egg-info/SOURCES.txt
src/restible_swagger.egg-info/dependency_links.txt
src/restible_swagger.egg-info/requires.txt
src/restible_swagger.egg-info/top_level.txt