Metadata-Version: 1.1
Name: restible-swagger
Version: 0.3.2
Summary: Generate OpenAPI spec for restible resources
Home-page: https://github.com/novopl/restible-swagger
Author: Mateusz 'novo' Klos
Author-email: novopl@gmail.com
License: MIT
Keywords: restible swagger OpenAPI REST restapi
Platform: UNKNOWN
Classifier: Development Status :: 4 - Beta
Classifier: Topic :: Utilities
Classifier: Intended Audience :: Developers
Classifier: Programming Language :: Python
Classifier: License :: OSI Approved :: MIT License
